funapi/__init__.py
funocr-0.0.1.dist-info/LICENSE
funocr-0.0.1.dist-info/METADATA
funocr-0.0.1.dist-info/WHEEL
funocr-0.0.1.dist-info/entry_points.txt
funocr-0.0.1.dist-info/top_level.txt
funocr-0.0.1.dist-info/RECORD
